setup.py
zrok/__init__.py
zrok/access.py
zrok/dialer.py
zrok/listener.py
zrok/model.py
zrok/overview.py
zrok/share.py
zrok/environment/__init__.py
zrok/environment/dirs.py
zrok/environment/root.py
zrok_api/__init__.py
zrok_api/api_client.py
zrok_api/configuration.py
zrok_api/rest.py
zrok_api/api/__init__.py
zrok_api/api/account_api.py
zrok_api/api/admin_api.py
zrok_api/api/environment_api.py
zrok_api/api/metadata_api.py
zrok_api/api/share_api.py
zrok_api/models/__init__.py
zrok_api/models/access_request.py
zrok_api/models/access_response.py
zrok_api/models/auth_user.py
zrok_api/models/configuration.py
zrok_api/models/create_frontend_request.py
zrok_api/models/create_frontend_response.py
zrok_api/models/delete_frontend_request.py
zrok_api/models/disable_request.py
zrok_api/models/enable_request.py
zrok_api/models/enable_response.py
zrok_api/models/environment.py
zrok_api/models/environment_and_resources.py
zrok_api/models/environments.py
zrok_api/models/error_message.py
zrok_api/models/frontend.py
zrok_api/models/frontends.py
zrok_api/models/identity_body.py
zrok_api/models/inline_response201.py
zrok_api/models/invite_request.py
zrok_api/models/invite_token_generate_request.py
zrok_api/models/login_request.py
zrok_api/models/login_response.py
zrok_api/models/metrics.py
zrok_api/models/metrics_sample.py
zrok_api/models/overview.py
zrok_api/models/password_requirements.py
zrok_api/models/principal.py
zrok_api/models/public_frontend.py
zrok_api/models/public_frontend_list.py
zrok_api/models/register_request.py
zrok_api/models/register_response.py
zrok_api/models/reset_password_request.py
zrok_api/models/reset_password_request_body.py
zrok_api/models/share.py
zrok_api/models/share_request.py
zrok_api/models/share_response.py
zrok_api/models/shares.py
zrok_api/models/spark_data.py
zrok_api/models/spark_data_sample.py
zrok_api/models/unaccess_request.py
zrok_api/models/unshare_request.py
zrok_api/models/update_frontend_request.py
zrok_api/models/update_share_request.py
zrok_sdk_kentest.egg-info/PKG-INFO
zrok_sdk_kentest.egg-info/SOURCES.txt
zrok_sdk_kentest.egg-info/dependency_links.txt
zrok_sdk_kentest.egg-info/requires.txt
zrok_sdk_kentest.egg-info/top_level.txt