Metadata-Version: 2.1
Name: zrok-sdk-kentest
Version: 0.0.41901
Summary: zrok
Home-page: https://zrok.io
Author-email: cameron.otts@netfoundry.io
Keywords: Swagger,zrok
Requires-Python: >=3.10
Requires-Dist: urllib3>=1.15
Requires-Dist: six>=1.10
Requires-Dist: certifi
Requires-Dist: python-dateutil
